LICENSE
MANIFEST.in
README.rst
mpdkeys
setup.py
osxmpdkeys/__init__.py
osxmpdkeys/client.py
osxmpdkeys.egg-info/PKG-INFO
osxmpdkeys.egg-info/SOURCES.txt
osxmpdkeys.egg-info/dependency_links.txt
osxmpdkeys.egg-info/requires.txt
osxmpdkeys.egg-info/top_level.txt