Metadata-Version: 1.1
Name: osxmpdkeys
Version: 1.0.0
Summary: Control mpd with the OS X media keys.
Home-page: https://github.com/pushrax/osxmpdkeys
Author: Justin Li
Author-email: jli@j-li.net
License: MIT
Platform: UNKNOWN
Classifier: Development Status :: 5 - Production/Stable
Classifier: Environment :: Console
Classifier: Environment :: MacOS X
Classifier: Intended Audience :: End Users/Desktop
Classifier: License :: OSI Approved :: MIT License
Classifier: Operating System :: MacOS
Classifier: Programming Language :: Python
Classifier: Programming Language :: Python :: 2.7
Classifier: Programming Language :: Python :: 3
Classifier: Programming Language :: Python :: 3.2
Classifier: Programming Language :: Python :: 3.3
Classifier: Programming Language :: Python :: 3.4
Classifier: Topic :: Multimedia :: Sound/Audio :: Players
